README.rst
setup.py
PyStratum_pgSQL.egg-info/PKG-INFO
PyStratum_pgSQL.egg-info/SOURCES.txt
PyStratum_pgSQL.egg-info/dependency_links.txt
PyStratum_pgSQL.egg-info/requires.txt
PyStratum_pgSQL.egg-info/top_level.txt
pystratum_pgsql/PgSqlConnector.py
pystratum_pgsql/PgSqlDataLayer.py
pystratum_pgsql/PgSqlDefaultConnector.py
pystratum_pgsql/PgSqlMetadataDataLayer.py
pystratum_pgsql/__init__.py
pystratum_pgsql/backend/PgSqlBackend.py
pystratum_pgsql/backend/PgSqlConstantWorker.py
pystratum_pgsql/backend/PgSqlRoutineLoaderWorker.py
pystratum_pgsql/backend/PgSqlRoutineWrapperGeneratorWorker.py
pystratum_pgsql/backend/PgSqlWorker.py
pystratum_pgsql/backend/__init__.py
pystratum_pgsql/helper/PgSqlDataTypeHelper.py
pystratum_pgsql/helper/PgSqlRoutineLoaderHelper.py
pystratum_pgsql/helper/__init__.py
pystratum_pgsql/wrapper/PgSqlFunctionsWrapper.py
pystratum_pgsql/wrapper/PgSqlLogWrapper.py
pystratum_pgsql/wrapper/PgSqlNoneWrapper.py
pystratum_pgsql/wrapper/PgSqlRow0Wrapper.py
pystratum_pgsql/wrapper/PgSqlRow1Wrapper.py
pystratum_pgsql/wrapper/PgSqlRowsWithIndexWrapper.py
pystratum_pgsql/wrapper/PgSqlRowsWithKeyWrapper.py
pystratum_pgsql/wrapper/PgSqlRowsWrapper.py
pystratum_pgsql/wrapper/PgSqlSingleton0Wrapper.py
pystratum_pgsql/wrapper/PgSqlSingleton1Wrapper.py
pystratum_pgsql/wrapper/PgSqlTableWrapper.py
pystratum_pgsql/wrapper/PgSqlWrapper.py
pystratum_pgsql/wrapper/__init__.py